envyconfig/__init__.py
envyconfig/exceptions/ConfigurationError.py
envyconfig/exceptions/InterpolationStringFormatError.py
envyconfig/exceptions/SecretNotFoundError.py
envyconfig/exceptions/__init__.py
envyconfig/lib/__init__.py
envyconfig/lib/loader.py
envyconfig/lib/methods.py
envyconfig-1.2.1.dist-info/LICENSE
envyconfig-1.2.1.dist-info/METADATA
envyconfig-1.2.1.dist-info/WHEEL
envyconfig-1.2.1.dist-info/top_level.txt
envyconfig-1.2.1.dist-info/RECORD
