Metadata-Version: 2.1
Name: envyconfig
Version: 1.2.1
Summary: YAML reader with ENV interpolation.
Home-page: https://github.com/geirem/envyconfig
Author: https://github.com/geirem
Author-email: geiremb@gmail.com
License: UNKNOWN
Project-URL: Bug Reports, https://github.com/geirem/envyconfig/issues
Project-URL: Funding, https://donate.pypi.org
Project-URL: Source, https://github.com/geirem/envyconfig/
Keywords: configtools development
Platform: UNKNOWN
Classifier: Development Status :: 4 - Beta
Classifier: Intended Audience :: Developers
Classifier: Topic :: Software Development
Classifier: License :: CC0 1.0 Universal (CC0 1.0) Public Domain Dedication
Classifier: Programming Language :: Python :: 3.8
Classifier: Programming Language :: Python :: 3 :: Only
Requires-Python: >=3.8
Provides-Extra: googlesecrets
Requires-Dist: google-cloud-secret-manager ; extra == 'googlesecrets'
Provides-Extra: test
Requires-Dist: pytest ; extra == 'test'
